networkx_mcp/__init__.py
networkx_mcp/__main__.py
networkx_mcp/__version__.py
networkx_mcp/cli.py
networkx_mcp/errors.py
networkx_mcp/features.py
networkx_mcp/server.py
networkx_mcp/server_fastmcp.py
networkx_mcp/server_legacy.py
networkx_mcp/server_minimal.py
networkx_mcp/config/production.py
networkx_mcp/core/__init__.py
networkx_mcp/core/algorithms.py
networkx_mcp/core/base.py
networkx_mcp/core/config.py
networkx_mcp/core/container.py
networkx_mcp/core/edge_ops.py
networkx_mcp/core/graceful_shutdown.py
networkx_mcp/core/graph_operations.py
networkx_mcp/core/io_handlers.py
networkx_mcp/core/node_ops.py
networkx_mcp/core/service_config.py
networkx_mcp/core/storage_manager.py
networkx_mcp/core/thread_safe_graph_manager.py
networkx_mcp/core/io/__init__.py
networkx_mcp/core/io/base_handler.py
networkx_mcp/core/io/csv_handler.py
networkx_mcp/core/io/excel_handler.py
networkx_mcp/core/io/gml_handler.py
networkx_mcp/core/io/graphml_handler.py
networkx_mcp/core/io/json_handler.py
networkx_mcp/enterprise/__init__.py
networkx_mcp/enterprise/auth.py
networkx_mcp/enterprise/config.py
networkx_mcp/enterprise/monitoring.py
networkx_mcp/enterprise/rate_limiting.py
networkx_mcp/enterprise/server.py
networkx_mcp/handlers/__init__.py
networkx_mcp/handlers/algorithms.py
networkx_mcp/handlers/graph_ops.py
networkx_mcp/io/__init__.py
networkx_mcp/io/base.py
networkx_mcp/io/graphml.py
networkx_mcp/schemas/__init__.py
networkx_mcp/schemas/graph_schemas.py
networkx_mcp/security/__init__.py
networkx_mcp/security/audit.py
networkx_mcp/security/auth.py
networkx_mcp/security/file_security.py
networkx_mcp/security/input_validation.py
networkx_mcp/security/middleware.py
networkx_mcp/security/rate_limiting.py
networkx_mcp/security/resource_limits.py
networkx_mcp/security/validation.py
networkx_mcp/security/validator.py
networkx_mcp/security_fortress/__init__.py
networkx_mcp/security_fortress/fortress_server.py
networkx_mcp/security_fortress/monitoring.py
networkx_mcp_server-2.0.0.dist-info/licenses/LICENSE
networkx_mcp_server-2.0.0.dist-info/METADATA
networkx_mcp_server-2.0.0.dist-info/WHEEL
networkx_mcp_server-2.0.0.dist-info/entry_points.txt
networkx_mcp_server-2.0.0.dist-info/top_level.txt
networkx_mcp_server-2.0.0.dist-info/RECORD
