Metadata-Version: 2.4
Name: networkx-mcp-server
Version: 2.0.0
Summary: NetworkX MCP Server with Security Fortress - Enterprise-grade secure graph analysis with AI-powered threat detection
Home-page: https://github.com/brightliu/networkx-mcp-server
Author: NetworkX MCP Team
Author-email: Bright Liu <brightliu@college.harvard.edu>
Maintainer-email: Bright Liu <brightliu@college.harvard.edu>
License: MIT
Project-URL: Homepage, https://github.com/Bright-L01/networkx-mcp-server
Project-URL: Repository, https://github.com/Bright-L01/networkx-mcp-server
Project-URL: Issues, https://github.com/Bright-L01/networkx-mcp-server/issues
Keywords: networkx,graph,analysis,mcp,ai,claude,visualization,network,centrality,community,security,fortress,threat-detection,zero-trust,enterprise
Classifier: Development Status :: 5 - Production/Stable
Classifier: Intended Audience :: Developers
Classifier: Intended Audience :: Science/Research
Classifier: License :: OSI Approved :: MIT License
Classifier: Programming Language :: Python :: 3
Classifier: Programming Language :: Python :: 3.11
Classifier: Programming Language :: Python :: 3.12
Classifier: Topic :: Scientific/Engineering :: Information Analysis
Classifier: Topic :: Scientific/Engineering :: Visualization
Classifier: Topic :: Software Development :: Libraries :: Python Modules
Classifier: Topic :: Internet :: WWW/HTTP :: Dynamic Content
Classifier: Environment :: Console
Classifier: Operating System :: OS Independent
Requires-Python: >=3.11
License-File: LICENSE
Requires-Dist: networkx>=3.0
Requires-Dist: numpy>=1.21.0
Requires-Dist: matplotlib>=3.5.0
Provides-Extra: dev
Requires-Dist: pytest>=7.0.0; extra == "dev"
Requires-Dist: pytest-asyncio>=0.21.0; extra == "dev"
Requires-Dist: pytest-cov>=4.0.0; extra == "dev"
Requires-Dist: coverage>=7.0.0; extra == "dev"
Requires-Dist: black>=24.0.0; extra == "dev"
Requires-Dist: ruff>=0.8.0; extra == "dev"
Requires-Dist: psutil>=5.9.0; extra == "dev"
Requires-Dist: hypothesis>=6.0.0; extra == "dev"
Requires-Dist: pandas>=1.3.0; extra == "dev"
Requires-Dist: requests>=2.28.0; extra == "dev"
Provides-Extra: excel
Requires-Dist: pandas>=1.3.0; extra == "excel"
Requires-Dist: openpyxl>=3.0.0; extra == "excel"
Provides-Extra: scipy
Requires-Dist: scipy>=1.7.0; extra == "scipy"
Provides-Extra: enterprise
Requires-Dist: authlib>=1.3.0; extra == "enterprise"
Requires-Dist: pyjwt>=2.8.0; extra == "enterprise"
Requires-Dist: pydantic>=2.5.0; extra == "enterprise"
Requires-Dist: pydantic-settings>=2.1.0; extra == "enterprise"
Requires-Dist: structlog>=23.2.0; extra == "enterprise"
Requires-Dist: prometheus-client>=0.19.0; extra == "enterprise"
Requires-Dist: aiohttp>=3.9.0; extra == "enterprise"
Requires-Dist: slowapi>=0.1.9; extra == "enterprise"
Requires-Dist: cryptography>=41.0.0; extra == "enterprise"
Requires-Dist: psutil>=5.9.0; extra == "enterprise"
Requires-Dist: docker>=7.0.0; extra == "enterprise"
Provides-Extra: full
Requires-Dist: pandas>=1.3.0; extra == "full"
Requires-Dist: scipy>=1.7.0; extra == "full"
Requires-Dist: matplotlib>=3.4.0; extra == "full"
Requires-Dist: openpyxl>=3.0.0; extra == "full"
Requires-Dist: authlib>=1.3.0; extra == "full"
Requires-Dist: pyjwt>=2.8.0; extra == "full"
Requires-Dist: pydantic>=2.5.0; extra == "full"
Requires-Dist: pydantic-settings>=2.1.0; extra == "full"
Requires-Dist: structlog>=23.2.0; extra == "full"
Requires-Dist: prometheus-client>=0.19.0; extra == "full"
Requires-Dist: aiohttp>=3.9.0; extra == "full"
Requires-Dist: slowapi>=0.1.9; extra == "full"
Requires-Dist: cryptography>=41.0.0; extra == "full"
Requires-Dist: psutil>=5.9.0; extra == "full"
Requires-Dist: docker>=7.0.0; extra == "full"
Dynamic: license-file
